match_pattern/__init__.py
match_pattern/pattern.py
match_pattern/pattern_test.py
match_pattern-0.1.1.dist-info/METADATA
match_pattern-0.1.1.dist-info/WHEEL
match_pattern-0.1.1.dist-info/top_level.txt
match_pattern-0.1.1.dist-info/RECORD
